sanic_restful_resources/__init__.py
sanic_restful_resources/sanic_restful_resources.py
sanic_restful_resources-0.2.0.dist-info/LICENSE
sanic_restful_resources-0.2.0.dist-info/METADATA
sanic_restful_resources-0.2.0.dist-info/WHEEL
sanic_restful_resources-0.2.0.dist-info/top_level.txt
sanic_restful_resources-0.2.0.dist-info/RECORD
