Metadata-Version: 2.1
Name: sanic-restful-resources
Version: 0.2.0
Summary: The library for writing RESTful APIs with sanic
Home-page: https://github.com/michaelkrukov/sanic-restful-resources
Author: Michael Krukov
Author-email: krukov.michael@ya.ru
License: UNKNOWN
Keywords: restful,rest,api,sanic,web,server
Platform: UNKNOWN
Classifier: Programming Language :: Python :: 3
Classifier: Programming Language :: Python :: 3 :: Only
Classifier: License :: OSI Approved :: MIT License
Classifier: Operating System :: OS Independent
Classifier: Intended Audience :: Developers
Requires-Python: >=3.5
Requires-Dist: sanic (>=19.12.2)
Requires-Dist: schematics (>=2.1.0)
